{
  "Name": "Logic Apps Standard Contributor (Preview)",
  "Id": "ad710c24-b039-4e85-a019-deb4a06e8570",
  "IsCustom": false,
  "Description": "You can manage all aspects of a Standard logic app and workflows. You can't change access or ownership.",
  "Actions": [
    "Microsoft.Authorization/*/read",
    "Microsoft.Insights/alertRules/*",
    "Microsoft.Resources/deployments/operations/read",
    "Microsoft.Resources/subscriptions/operationresults/read",
    "Microsoft.Resources/subscriptions/resourceGroups/read",
    "Microsoft.Support/*",
    "Microsoft.Web/*/read",
    "Microsoft.Web/certificates/*",
    "Microsoft.Web/connectionGateways/*",
    "Microsoft.Web/connections/*",
    "Microsoft.Web/customApis/*",
    "Microsoft.Web/serverFarms/*",
    "Microsoft.Web/sites/*"
  ],
  "NotActions": [],
  "DataActions": [],
  "NotDataActions": [],
  "AssignableScopes": [
    "/"
  ],
  "Condition": null,
  "ConditionVersion": null
}
